fastapi_decorators/__init__.py
fastapi_decorators/decorators.py
fastapi_decorators/py.typed
fastapi_decorators/types.py
fastapi_decorators-1.0.19.dist-info/METADATA
fastapi_decorators-1.0.19.dist-info/WHEEL
fastapi_decorators-1.0.19.dist-info/licenses/LICENSE
fastapi_decorators-1.0.19.dist-info/RECORD
