Metadata-Version: 2.4
Name: fastapi-decorators
Version: 1.0.19
Summary: Create decorators for your endpoints using FastAPI dependencies.
Project-URL: Homepage, https://github.com/Minibrams/fastapi-decorators
Project-URL: Documentation, https://github.com/Minibrams/fastapi-decorators
Project-URL: Repository, https://github.com/Minibrams/fastapi-decorators
Project-URL: Issues, https://github.com/Minibrams/fastapi-decorators/issues
Author-email: Anders Brams <anders@brams.dk>
License: MIT License
License-File: LICENSE
Keywords: decorators,dependencies,dependency,fastapi,middleware
Classifier: Development Status :: 4 - Beta
Classifier: Environment :: Web Environment
Classifier: Framework :: FastAPI
Classifier: Intended Audience :: Developers
Classifier: License :: OSI Approved :: MIT License
Classifier: Operating System :: OS Independent
Classifier: Programming Language :: Python
Classifier: Programming Language :: Python :: 3
Classifier: Programming Language :: Python :: 3 :: Only
Classifier: Programming Language :: Python :: 3.8
Classifier: Programming Language :: Python :: 3.9
Classifier: Programming Language :: Python :: 3.10
Classifier: Programming Language :: Python :: 3.11
Classifier: Programming Language :: Python :: 3.12
Classifier: Topic :: Internet
Classifier: Topic :: Internet :: WWW/HTTP
Classifier: Topic :: Internet :: WWW/HTTP :: HTTP Servers
Classifier: Topic :: Software Development
Classifier: Topic :: Software Development :: Libraries
Classifier: Topic :: Software Development :: Libraries :: Application Frameworks
Classifier: Topic :: Software Development :: Libraries :: Python Modules
Classifier: Typing :: Typed
Requires-Python: >=3.8
Requires-Dist: fastapi>=0.70.0
